django_wsgi/__init__.py
django_wsgi/embedded_wsgi.py
django_wsgi/exc.py
django_wsgi/handler.py
django_wsgi/middleware.py
django_wsgi-1.0b1.dist-info/DESCRIPTION.rst
django_wsgi-1.0b1.dist-info/METADATA
django_wsgi-1.0b1.dist-info/RECORD
django_wsgi-1.0b1.dist-info/WHEEL
django_wsgi-1.0b1.dist-info/metadata.json
django_wsgi-1.0b1.dist-info/top_level.txt
tests/dummy_django_project/__init__.py
tests/dummy_django_project/settings.py
tests/dummy_django_project/urls.py
